hack4u/__init__.py
hack4u/courses.py
hack4u/utils.py
jc_cybersec_hack4u-0.1.1.dist-info/METADATA
jc_cybersec_hack4u-0.1.1.dist-info/WHEEL
jc_cybersec_hack4u-0.1.1.dist-info/top_level.txt
jc_cybersec_hack4u-0.1.1.dist-info/RECORD
