Metadata-Version: 2.4
Name: jc_cybersec_hack4u
Version: 0.1.1
Summary: Una biblioteca para consultar cursos de hack4u.
Home-page: https://hack4u.io
Author: Javier Criado
Dynamic: author
Dynamic: description
Dynamic: description-content-type
Dynamic: home-page
Dynamic: summary
